html_opener_library/__init__.py
html_opener_library-0.1.0.dist-info/METADATA
html_opener_library-0.1.0.dist-info/WHEEL
html_opener_library-0.1.0.dist-info/top_level.txt
html_opener_library-0.1.0.dist-info/RECORD
