Metadata-Version: 2.1
Name: html_opener_library
Version: 0.1.0
Summary: A library to open HTML files periodically in a browser.
Author: Kriperovich
Requires-Python: >=3.6
